w3ml/__init__.py
w3ml/models/__init__.py
w3ml/models/contrib/__init__.py
w3ml/models/contrib/automl_binary.py
w3ml/models/contrib/automl_multiclass.py
w3ml/models/contrib/automl_multilabel.py
w3ml/utils/__init__.py
w3ml-1.0.0.dist-info/LICENSE
w3ml-1.0.0.dist-info/METADATA
w3ml-1.0.0.dist-info/WHEEL
w3ml-1.0.0.dist-info/top_level.txt
w3ml-1.0.0.dist-info/RECORD
